{
  "id": "20260709-025",
  "title": "How Donkey Kong Toppled Atari",
  "source": "hacker_news",
  "source_url": "https://dfarq.homeip.net/how-donkey-kong-toppled-atari/",
  "summary": "文章分析《大金刚》如何导致雅达利在游戏行业中的衰落。",
  "translated_summary": "The article analyzes how Donkey Kong contributed to Atari's decline in the video game industry.",
  "tags": [
    "Donkey Kong",
    "Atari",
    "video game history"
  ],
  "category": "opinion",
  "language": "en",
  "collected_at": "2026-07-09T18:48:19.166303+08:00",
  "status": "pending",
  "score": 0.3
}