{
  "id": "20260707-032",
  "title": "GLM 5.2 and the coming AI margin collapse",
  "source": "hacker_news",
  "source_url": "https://martinalderson.com/posts/the-upcoming-ai-margin-collapse-part-1-glm-5-2/",
  "summary": "文章分析GLM 5.2模型发布将导致AI行业利润率崩溃，引发市场格局变化。",
  "translated_summary": "The article analyzes how the release of GLM 5.2 will lead to a collapse in AI industry margins, triggering changes in market structure.",
  "tags": [
    "GLM 5.2",
    "AI margin collapse",
    "market analysis"
  ],
  "category": "opinion",
  "language": "en",
  "collected_at": "2026-07-07T18:49:20.621432+08:00",
  "status": "pending",
  "score": 0.75
}