{
  "id": "20260711-037",
  "title": "Laylo (YC S20) Is Hiring a Head of Finance",
  "source": "hacker_news",
  "source_url": "https://www.ycombinator.com/companies/laylo/jobs/qce41D2-head-of-finance",
  "summary": "Laylo（YC S20）正在招聘财务主管。",
  "translated_summary": "Laylo (YC S20) is hiring a Head of Finance.",
  "tags": [
    "hiring",
    "finance",
    "startup"
  ],
  "category": "tool",
  "language": "en",
  "collected_at": "2026-07-11T17:20:42.793592+08:00",
  "status": "pending",
  "score": 0.1
}