{
  "id": "20260704-036",
  "title": "Infracost (YC W21) Is Hiring a Marketing Lead to Shift FinOps Left",
  "source": "hacker_news",
  "source_url": "https://www.ycombinator.com/companies/infracost/jobs/YTJcFwr-marketing-lead",
  "summary": "Infracost（YC W21）正在招聘营销负责人，以推动FinOps左移策略。",
  "translated_summary": "Infracost (YC W21) is hiring a Marketing Lead to shift FinOps left.",
  "tags": [
    "Infracost",
    "FinOps",
    "招聘"
  ],
  "category": "opinion",
  "language": "en",
  "collected_at": "2026-07-04T18:02:25.698014+08:00",
  "status": "pending",
  "score": 0.3
}